coas_core/__init__.py
coas_core/asgi.py
coas_core/settings.py
coas_core/urls.py
coas_core/wsgi.py
coasc/__init__.py
coasc/admin.py
coasc/apps.py
coasc/exceptions.py
coasc/models.py
coasc/tests.py
coasc/views.py
coasc/migrations/0001_initial.py
coasc/migrations/0002_rename_parent_ac_impersonalaccount_p_ac_and_more.py
coasc/migrations/0003_rename_account_split_ac_rename_amount_split_am_and_more.py
coasc/migrations/0004_rename_impersonalaccount_impersonalac.py
coasc/migrations/0005_ac_alter_split_ac_delete_impersonalac.py
coasc/migrations/0006_ac_t_ac.py
coasc/migrations/0007_member.py
coasc/migrations/0008_ac_mem.py
coasc/migrations/0009_transaction_date_created.py
coasc/migrations/0010_rename_date_created_transaction_created_at.py
coasc/migrations/0011_transaction_tx_date.py
coasc/migrations/0012_alter_ac_cat.py
coasc/migrations/0013_alter_transaction_desc.py
coasc/migrations/0014_alter_ac_cat.py
coasc/migrations/__init__.py
django_coasc-0.1.2.dist-info/METADATA
django_coasc-0.1.2.dist-info/WHEEL
django_coasc-0.1.2.dist-info/top_level.txt
django_coasc-0.1.2.dist-info/RECORD
