Metadata-Version: 2.4
Name: django-coasc
Version: 0.1.2
Summary: Django application providing a solid foundation for double-entry bookkeeping systems
Author: Suresh Thagunna
Project-URL: Homepage, https://github.com/suresh466/django-coasc
Keywords: django,accounting,bookkeeping,double-entry,finance,cooperative
Requires-Python: >=3.13
Requires-Dist: django>=5.1.7
